chatai/__init__.py
chatai/__main__.py
chatai/chatbotgui.py
chatai/defaulticon.png
chatbotai_gui-2.1.1.post230829038032890382908901890812039.dist-info/METADATA
chatbotai_gui-2.1.1.post230829038032890382908901890812039.dist-info/WHEEL
chatbotai_gui-2.1.1.post230829038032890382908901890812039.dist-info/top_level.txt
chatbotai_gui-2.1.1.post230829038032890382908901890812039.dist-info/RECORD
