Metadata-Version: 2.2
Name: chatbotai-gui
Version: 2.1.1.post230829038032890382908901890812039
Summary: A chatbot GUI that uses OpenAI, MetaAI, and Google Generative AI.
Author: ProgMEM-CC
License: AGPL-3.0-or-later
Requires-Dist: openai
Requires-Dist: meta_ai_api
Requires-Dist: google-generativeai
Requires-Dist: anthropic
Provides-Extra: dev
Requires-Dist: pytest; extra == "dev"
Requires-Dist: pytest-cov; extra == "dev"
Requires-Dist: coverage; extra == "dev"
Requires-Dist: flake8; extra == "dev"
Requires-Dist: black; extra == "dev"
Requires-Dist: isort; extra == "dev"
